LICENSE
README.rst
setup.py
ezmodel/__init__.py
ezmodel/fit.py
ezmodel/version.py
ezmodel.egg-info/PKG-INFO
ezmodel.egg-info/SOURCES.txt
ezmodel.egg-info/dependency_links.txt
ezmodel.egg-info/requires.txt
ezmodel.egg-info/top_level.txt
ezmodel/core/__init__.py
ezmodel/core/benchmark.py
ezmodel/core/factory.py
ezmodel/core/model.py
ezmodel/core/partitioning.py
ezmodel/core/selection.py
ezmodel/core/transformation.py
ezmodel/models/__init__.py
ezmodel/models/forest.py
ezmodel/models/gpflow.py
ezmodel/models/gpy.py
ezmodel/models/idw.py
ezmodel/models/knn.py
ezmodel/models/kriging.py
ezmodel/models/mean.py
ezmodel/models/pysotrbf.py
ezmodel/models/rbf.py
ezmodel/models/regression.py
ezmodel/models/smt.py
ezmodel/models/svr.py
ezmodel/usage/__init__.py
ezmodel/usage/usage_benchmark.py
ezmodel/usage/usage_fit.py
ezmodel/usage/models/__init__.py
ezmodel/usage/models/usage_gpflow.py
ezmodel/usage/models/usage_gpy.py
ezmodel/usage/models/usage_idw.py
ezmodel/usage/models/usage_kriging.py
ezmodel/usage/models/usage_nearest.py
ezmodel/usage/models/usage_rbf.py
ezmodel/usage/models/usage_smt.py
ezmodel/usage/models/usage_svr.py
ezmodel/util/__init__.py
ezmodel/util/dist.py
ezmodel/util/metrics.py
ezmodel/util/misc.py
ezmodel/util/sample_from_func.py
ezmodel/util/aggregate/__init__.py
ezmodel/util/aggregate/clearing.py
ezmodel/util/aggregate/front_wise.py
ezmodel/util/aggregate/grid.py
ezmodel/util/partitioning/__init__.py
ezmodel/util/partitioning/crossvalidation.py
ezmodel/util/partitioning/random.py
ezmodel/util/transformation/__init__.py
ezmodel/util/transformation/plog.py
ezmodel/util/transformation/standardization.py
ezmodel/util/transformation/stoch_tunneling.py
ezmodel/util/transformation/zero_to_one.py
tests/test_benchmark.py
tests/test_metrics.py
tests/test_normalization.py
tests/test_partitioning.py
tests/test_selection.py
tests/test_usage.py